i4sect/__init__.py
i4sect/i4sect.py
i4sect-0.0.3.dist-info/METADATA
i4sect-0.0.3.dist-info/WHEEL
i4sect-0.0.3.dist-info/top_level.txt
i4sect-0.0.3.dist-info/RECORD
