Metadata-Version: 2.1
Name: i4sect
Version: 0.0.3
Summary: intersection() caliculates intersection between two line segments
Home-page: https://github.com/KouichiMatsuda/isect
Author: MATSUDA, Kouichi
Author-email: kouichi.matsuda@gmail.com
License: MIT
Keywords: intersection intersection-between-two-lines
Platform: UNKNOWN
Classifier: License :: OSI Approved :: MIT License
Classifier: Programming Language :: Python :: 3.6
